{"metadata": {"dbt_schema_version": "https://schemas.getdbt.com/dbt/catalog/v1.json", "dbt_version": "1.8.3", "generated_at": "2024-07-18T11:10:25.537844Z", "invocation_id": "0cffce6d-7b00-45bb-ae35-cb4e60a5cdef", "env": {}}, "nodes": {"model.Energy_model.churn_address_test": {"metadata": {"type": "table", "schema": "grp_dataeng_dbt", "name": "churn_address_test", "database": "hive_metastore", "comment": null, "owner": "root"}, "columns": {"address_id": {"type": "integer", "index": 0, "name": "address_id", "comment": null}, "ilu_akey": {"type": "string", "index": 1, "name": "ilu_akey", "comment": null}, "UPRN": {"type": "string", "index": 2, "name": "UPRN", "comment": null}, "postcode": {"type": "string", "index": 3, "name": "postcode", "comment": null}, "property_type": {"type": "string", "index": 4, "name": "property_type", "comment": null}, "floor_area_sqm": {"type": "float", "index": 5, "name": "floor_area_sqm", "comment": null}, "building_volume_cubic_m": {"type": "float", "index": 6, "name": "building_volume_cubic_m", "comment": null}, "gas_annual_consumption": {"type": "float", "index": 7, "name": "gas_annual_consumption", "comment": null}, "ele_annual_consumption": {"type": "float", "index": 8, "name": "ele_annual_consumption", "comment": null}, "latitude": {"type": "float", "index": 9, "name": "latitude", "comment": null}, "longitude": {"type": "float", "index": 10, "name": "longitude", "comment": null}, "pes_region": {"type": "string", "index": 11, "name": "pes_region", "comment": null}, "wmis_region": {"type": "string", "index": 12, "name": "wmis_region", "comment": null}, "wmis_patch": {"type": "string", "index": 13, "name": "wmis_patch", "comment": null}, "geocode_multiplicity": {"type": "integer", "index": 14, "name": "geocode_multiplicity", "comment": null}, "postcode_density": {"type": "bigint", "index": 15, "name": "postcode_density", "comment": null}, "bedroom_count": {"type": "integer", "index": 16, "name": "bedroom_count", "comment": null}, "height_in_meters": {"type": "float", "index": 17, "name": "height_in_meters", "comment": null}, "mpan": {"type": "string", "index": 18, "name": "mpan", "comment": null}, "mprn": {"type": "string", "index": 19, "name": "mprn", "comment": null}, "gas_meter_type": {"type": "string", "index": 20, "name": "gas_meter_type", "comment": null}, "ele_meter_type": {"type": "string", "index": 21, "name": "ele_meter_type", "comment": null}, "eastings": {"type": "string", "index": 22, "name": "eastings", "comment": null}, "northings": {"type": "string", "index": 23, "name": "northings", "comment": null}, "rural_urban": {"type": "string", "index": 24, "name": "rural_urban", "comment": null}, "housing_tenure": {"type": "string", "index": 25, "name": "housing_tenure", "comment": null}, "property_age": {"type": "string", "index": 26, "name": "property_age", "comment": null}, "council_tax_band": {"type": "string", "index": 27, "name": "council_tax_band", "comment": null}, "burglary_rate": {"type": "string", "index": 28, "name": "burglary_rate", "comment": null}, "property_price": {"type": "float", "index": 29, "name": "property_price", "comment": null}, "date_last_sold": {"type": "date", "index": 30, "name": "date_last_sold", "comment": null}, "number_of_radiators": {"type": "string", "index": 31, "name": "number_of_radiators", "comment": null}, "epc_assessment_date": {"type": "date", "index": 32, "name": "epc_assessment_date", "comment": null}, "current_energy_efficiency_rating_band": {"type": "string", "index": 33, "name": "current_energy_efficiency_rating_band", "comment": null}, "heating_efficiency": {"type": "string", "index": 34, "name": "heating_efficiency", "comment": null}, "heating_type": {"type": "string", "index": 35, "name": "heating_type", "comment": null}, "co2_emissions_current_per_floor_area": {"type": "float", "index": 36, "name": "co2_emissions_current_per_floor_area", "comment": null}, "floor_energy_eff": {"type": "string", "index": 37, "name": "floor_energy_eff", "comment": null}, "mainheat_energy_eff": {"type": "string", "index": 38, "name": "mainheat_energy_eff", "comment": null}, "hot_water_energy_eff": {"type": "string", "index": 39, "name": "hot_water_energy_eff", "comment": null}, "lighting_energy_eff": {"type": "string", "index": 40, "name": "lighting_energy_eff", "comment": null}, "current_emissions": {"type": "float", "index": 41, "name": "current_emissions", "comment": null}, "photovoltaic_supply": {"type": "float", "index": 42, "name": "photovoltaic_supply", "comment": null}}, "stats": {"bytes": {"id": "bytes", "label": "bytes", "value": 42793527073, "include": true, "description": null}, "has_stats": {"id": "has_stats", "label": "Has Stats?", "value": true, "include": false, "description": "Indicates whether there are statistics for this table"}}, "unique_id": "model.Energy_model.churn_address_test"}, "model.Energy_model.churn_billing_test": {"metadata": {"type": "table", "schema": "grp_dataeng_dbt", "name": "churn_billing_test", "database": "hive_metastore", "comment": null, "owner": "root"}, "columns": {"account_id": {"type": "integer", "index": 0, "name": "account_id", "comment": null}, "bill_id": {"type": "bigint", "index": 1, "name": "bill_id", "comment": null}, "charge_id": {"type": "bigint", "index": 2, "name": "charge_id", "comment": null}, "bill_line_item_id": {"type": "bigint", "index": 3, "name": "bill_line_item_id", "comment": null}, "statement_id": {"type": "bigint", "index": 4, "name": "statement_id", "comment": null}, "commodity_uid": {"type": "string", "index": 5, "name": "commodity_uid", "comment": null}, "account_transaction_id": {"type": "bigint", "index": 6, "name": "account_transaction_id", "comment": null}, "bill_amount": {"type": "float", "index": 7, "name": "bill_amount", "comment": null}, "bill_period_from": {"type": "date", "index": 8, "name": "bill_period_from", "comment": null}, "bill_period_to": {"type": "date", "index": 9, "name": "bill_period_to", "comment": null}, "bill_created_date": {"type": "date", "index": 10, "name": "bill_created_date", "comment": null}, "charge_start_date": {"type": "date", "index": 11, "name": "charge_start_date", "comment": null}, "charge_end_date": {"type": "date", "index": 12, "name": "charge_end_date", "comment": null}, "elec_bill_status": {"type": "string", "index": 13, "name": "elec_bill_status", "comment": null}, "elec_bill_type": {"type": "string", "index": 14, "name": "elec_bill_type", "comment": null}, "elec_standing_charge": {"type": "float", "index": 15, "name": "elec_standing_charge", "comment": null}, "elec_num_days_billing": {"type": "integer", "index": 16, "name": "elec_num_days_billing", "comment": null}, "elec_daily_unit_consumption": {"type": "float", "index": 17, "name": "elec_daily_unit_consumption", "comment": null}, "elec_Units_consumption": {"type": "float", "index": 18, "name": "elec_Units_consumption", "comment": null}, "gas_bill_status": {"type": "string", "index": 19, "name": "gas_bill_status", "comment": null}, "gas_bill_type": {"type": "string", "index": 20, "name": "gas_bill_type", "comment": null}, "gas_standing_charge": {"type": "float", "index": 21, "name": "gas_standing_charge", "comment": null}, "gas_num_days_billing": {"type": "integer", "index": 22, "name": "gas_num_days_billing", "comment": null}, "gas_Units_consumption": {"type": "float", "index": 23, "name": "gas_Units_consumption", "comment": null}, "gas_daily_unit_consumption": {"type": "float", "index": 24, "name": "gas_daily_unit_consumption", "comment": null}, "mpxn": {"type": "bigint", "index": 25, "name": "mpxn", "comment": null}, "unit_rate": {"type": "float", "index": 26, "name": "unit_rate", "comment": null}}, "stats": {"bytes": {"id": "bytes", "label": "bytes", "value": 3706367137, "include": true, "description": null}, "has_stats": {"id": "has_stats", "label": "Has Stats?", "value": true, "include": false, "description": "Indicates whether there are statistics for this table"}}, "unique_id": "model.Energy_model.churn_billing_test"}, "model.Energy_model.churn_complaint_test": {"metadata": {"type": "table", "schema": "grp_dataeng_dbt", "name": "churn_complaint_test", "database": "hive_metastore", "comment": null, "owner": "root"}, "columns": {"customer_id": {"type": "string", "index": 0, "name": "customer_id", "comment": null}, "source_complaint_id": {"type": "string", "index": 1, "name": "source_complaint_id", "comment": null}, "complaint_type": {"type": "string", "index": 2, "name": "complaint_type", "comment": null}, "created_ts": {"type": "timestamp", "index": 3, "name": "created_ts", "comment": null}, "closed_ts": {"type": "timestamp", "index": 4, "name": "closed_ts", "comment": null}, "contact_reason_1": {"type": "string", "index": 5, "name": "contact_reason_1", "comment": null}, "contact_reason_2": {"type": "string", "index": 6, "name": "contact_reason_2", "comment": null}, "contact_reason_3": {"type": "string", "index": 7, "name": "contact_reason_3", "comment": null}, "source": {"type": "string", "index": 8, "name": "source", "comment": null}}, "stats": {"bytes": {"id": "bytes", "label": "bytes", "value": 2415458020, "include": true, "description": null}, "has_stats": {"id": "has_stats", "label": "Has Stats?", "value": true, "include": false, "description": "Indicates whether there are statistics for this table"}}, "unique_id": "model.Energy_model.churn_complaint_test"}, "model.Energy_model.churn_consumption_test": {"metadata": {"type": "table", "schema": "grp_dataeng_dbt", "name": "churn_consumption_test", "database": "hive_metastore", "comment": null, "owner": "root"}, "columns": {"current_account_id": {"type": "integer", "index": 0, "name": "current_account_id", "comment": null}, "consumption_item_id": {"type": "integer", "index": 1, "name": "consumption_item_id", "comment": null}, "mpxn": {"type": "bigint", "index": 2, "name": "mpxn", "comment": null}, "meter_point_type": {"type": "string", "index": 3, "name": "meter_point_type", "comment": null}, "recorded_date": {"type": "date", "index": 4, "name": "recorded_date", "comment": null}, "recorded_ts": {"type": "timestamp", "index": 5, "name": "recorded_ts", "comment": null}, "charge_start_date": {"type": "date", "index": 6, "name": "charge_start_date", "comment": null}, "charge_end_date": {"type": "date", "index": 7, "name": "charge_end_date", "comment": null}, "actual_or_estimated": {"type": "string", "index": 8, "name": "actual_or_estimated", "comment": null}, "meter_reading_source": {"type": "string", "index": 9, "name": "meter_reading_source", "comment": null}, "start_end_date_units_consumed": {"type": "float", "index": 10, "name": "start_end_date_units_consumed", "comment": null}, "unit_type_uid": {"type": "string", "index": 11, "name": "unit_type_uid", "comment": null}, "start_end_date_units_rate": {"type": "float", "index": 12, "name": "start_end_date_units_rate", "comment": null}, "standing_charge": {"type": "float", "index": 13, "name": "standing_charge", "comment": null}, "start_end_date_billed_amount": {"type": "float", "index": 14, "name": "start_end_date_billed_amount", "comment": null}, "meter_reading_value": {"type": "float", "index": 15, "name": "meter_reading_value", "comment": null}, "daily_unit_consumption": {"type": "float", "index": 16, "name": "daily_unit_consumption", "comment": null}, "days_consumed": {"type": "integer", "index": 17, "name": "days_consumed", "comment": null}, "quantity_energy_consumed": {"type": "float", "index": 18, "name": "quantity_energy_consumed", "comment": null}}, "stats": {"bytes": {"id": "bytes", "label": "bytes", "value": 23840619782, "include": true, "description": null}, "has_stats": {"id": "has_stats", "label": "Has Stats?", "value": true, "include": false, "description": "Indicates whether there are statistics for this table"}}, "unique_id": "model.Energy_model.churn_consumption_test"}, "model.Energy_model.churn_customer_test": {"metadata": {"type": "table", "schema": "grp_dataeng_dbt", "name": "churn_customer_test", "database": "hive_metastore", "comment": null, "owner": "root"}, "columns": {"customer_id": {"type": "string", "index": 0, "name": "customer_id", "comment": null}, "salutation": {"type": "string", "index": 1, "name": "salutation", "comment": null}, "vulrability": {"type": "integer", "index": 2, "name": "vulrability", "comment": null}, "marketing_consent": {"type": "string", "index": 3, "name": "marketing_consent", "comment": null}, "name": {"type": "string", "index": 4, "name": "name", "comment": null}, "email": {"type": "array", "index": 5, "name": "email", "comment": null}, "phone": {"type": "array", "index": 6, "name": "phone", "comment": null}, "gender": {"type": "string", "index": 7, "name": "gender", "comment": null}, "birth_dt": {"type": "timestamp", "index": 8, "name": "birth_dt", "comment": null}, "death_dt": {"type": "timestamp", "index": 9, "name": "death_dt", "comment": null}, "source_domain": {"type": "string", "index": 10, "name": "source_domain", "comment": null}}, "stats": {"bytes": {"id": "bytes", "label": "bytes", "value": 15443363493, "include": true, "description": null}, "has_stats": {"id": "has_stats", "label": "Has Stats?", "value": true, "include": false, "description": "Indicates whether there are statistics for this table"}}, "unique_id": "model.Energy_model.churn_customer_test"}, "model.Energy_model.churn_holding_test": {"metadata": {"type": "table", "schema": "grp_dataeng_dbt", "name": "churn_holding_test", "database": "hive_metastore", "comment": null, "owner": "root"}, "columns": {"mpxn": {"type": "string", "index": 0, "name": "mpxn", "comment": null}, "customer_id": {"type": "string", "index": 1, "name": "customer_id", "comment": null}, "supply_start_dt": {"type": "date", "index": 2, "name": "supply_start_dt", "comment": null}, "supply_end_dt": {"type": "date", "index": 3, "name": "supply_end_dt", "comment": null}, "migration_dt": {"type": "date", "index": 4, "name": "migration_dt", "comment": null}, "address_id": {"type": "string", "index": 5, "name": "address_id", "comment": null}, "account_id": {"type": "string", "index": 6, "name": "account_id", "comment": null}, "product_category": {"type": "string", "index": 7, "name": "product_category", "comment": null}, "product_name": {"type": "string", "index": 8, "name": "product_name", "comment": null}, "product_start_dt": {"type": "date", "index": 9, "name": "product_start_dt", "comment": null}, "product_end_dt": {"type": "date", "index": 10, "name": "product_end_dt", "comment": null}, "source_domain": {"type": "string", "index": 11, "name": "source_domain", "comment": null}}, "stats": {"bytes": {"id": "bytes", "label": "bytes", "value": 17321807228, "include": true, "description": null}, "has_stats": {"id": "has_stats", "label": "Has Stats?", "value": true, "include": false, "description": "Indicates whether there are statistics for this table"}}, "unique_id": "model.Energy_model.churn_holding_test"}, "model.Energy_model.churn_interaction_test": {"metadata": {"type": "table", "schema": "grp_dataeng_dbt", "name": "churn_interaction_test", "database": "hive_metastore", "comment": null, "owner": "root"}, "columns": {"interaction_id": {"type": "string", "index": 0, "name": "interaction_id", "comment": null}, "customer_id": {"type": "string", "index": 1, "name": "customer_id", "comment": null}, "direction": {"type": "string", "index": 2, "name": "direction", "comment": null}, "interaction_ts": {"type": "timestamp", "index": 3, "name": "interaction_ts", "comment": null}, "interaction_reason_l1": {"type": "string", "index": 4, "name": "interaction_reason_l1", "comment": null}, "interaction_reason_l2": {"type": "string", "index": 5, "name": "interaction_reason_l2", "comment": null}, "interaction_reason_l3": {"type": "string", "index": 6, "name": "interaction_reason_l3", "comment": null}, "connected_to_agent": {"type": "boolean", "index": 7, "name": "connected_to_agent", "comment": null}, "queue_time": {"type": "integer", "index": 8, "name": "queue_time", "comment": null}, "talk_time": {"type": "integer", "index": 9, "name": "talk_time", "comment": null}, "interaction_type": {"type": "string", "index": 10, "name": "interaction_type", "comment": null}, "interaction_source": {"type": "string", "index": 11, "name": "interaction_source", "comment": null}}, "stats": {"bytes": {"id": "bytes", "label": "bytes", "value": 13149942918, "include": true, "description": null}, "has_stats": {"id": "has_stats", "label": "Has Stats?", "value": true, "include": false, "description": "Indicates whether there are statistics for this table"}}, "unique_id": "model.Energy_model.churn_interaction_test"}, "model.Energy_model.churn_nps_test": {"metadata": {"type": "table", "schema": "grp_dataeng_dbt", "name": "churn_nps_test", "database": "hive_metastore", "comment": null, "owner": "root"}, "columns": {"nps_survey_id": {"type": "string", "index": 0, "name": "nps_survey_id", "comment": null}, "customer_id": {"type": "string", "index": 1, "name": "customer_id", "comment": null}, "survey_ts": {"type": "timestamp", "index": 2, "name": "survey_ts", "comment": null}, "nps_score": {"type": "integer", "index": 3, "name": "nps_score", "comment": null}, "survey_type": {"type": "string", "index": 4, "name": "survey_type", "comment": null}, "source": {"type": "string", "index": 5, "name": "source", "comment": null}}, "stats": {"bytes": {"id": "bytes", "label": "bytes", "value": 4290417397, "include": true, "description": null}, "has_stats": {"id": "has_stats", "label": "Has Stats?", "value": true, "include": false, "description": "Indicates whether there are statistics for this table"}}, "unique_id": "model.Energy_model.churn_nps_test"}}, "sources": {"source.Energy_model.grp_dataeng_dev.churn_address": {"metadata": {"type": "table", "schema": "grp_dataeng_dev", "name": "churn_address", "database": "hive_metastore", "comment": null, "owner": "root"}, "columns": {"address_id": {"type": "integer", "index": 0, "name": "address_id", "comment": null}, "ilu_akey": {"type": "string", "index": 1, "name": "ilu_akey", "comment": null}, "UPRN": {"type": "string", "index": 2, "name": "UPRN", "comment": null}, "postcode": {"type": "string", "index": 3, "name": "postcode", "comment": null}, "property_type": {"type": "string", "index": 4, "name": "property_type", "comment": null}, "floor_area_sqm": {"type": "float", "index": 5, "name": "floor_area_sqm", "comment": null}, "building_volume_cubic_m": {"type": "float", "index": 6, "name": "building_volume_cubic_m", "comment": null}, "gas_annual_consumption": {"type": "float", "index": 7, "name": "gas_annual_consumption", "comment": null}, "ele_annual_consumption": {"type": "float", "index": 8, "name": "ele_annual_consumption", "comment": null}, "latitude": {"type": "float", "index": 9, "name": "latitude", "comment": null}, "longitude": {"type": "float", "index": 10, "name": "longitude", "comment": null}, "pes_region": {"type": "string", "index": 11, "name": "pes_region", "comment": null}, "wmis_region": {"type": "string", "index": 12, "name": "wmis_region", "comment": null}, "wmis_patch": {"type": "string", "index": 13, "name": "wmis_patch", "comment": null}, "geocode_multiplicity": {"type": "integer", "index": 14, "name": "geocode_multiplicity", "comment": null}, "postcode_density": {"type": "bigint", "index": 15, "name": "postcode_density", "comment": null}, "bedroom_count": {"type": "integer", "index": 16, "name": "bedroom_count", "comment": null}, "height_in_meters": {"type": "float", "index": 17, "name": "height_in_meters", "comment": null}, "mpan": {"type": "string", "index": 18, "name": "mpan", "comment": null}, "mprn": {"type": "string", "index": 19, "name": "mprn", "comment": null}, "gas_meter_type": {"type": "string", "index": 20, "name": "gas_meter_type", "comment": null}, "ele_meter_type": {"type": "string", "index": 21, "name": "ele_meter_type", "comment": null}, "eastings": {"type": "string", "index": 22, "name": "eastings", "comment": null}, "northings": {"type": "string", "index": 23, "name": "northings", "comment": null}, "rural_urban": {"type": "string", "index": 24, "name": "rural_urban", "comment": null}, "housing_tenure": {"type": "string", "index": 25, "name": "housing_tenure", "comment": null}, "property_age": {"type": "string", "index": 26, "name": "property_age", "comment": null}, "council_tax_band": {"type": "string", "index": 27, "name": "council_tax_band", "comment": null}, "burglary_rate": {"type": "string", "index": 28, "name": "burglary_rate", "comment": null}, "property_price": {"type": "float", "index": 29, "name": "property_price", "comment": null}, "date_last_sold": {"type": "date", "index": 30, "name": "date_last_sold", "comment": null}, "number_of_radiators": {"type": "string", "index": 31, "name": "number_of_radiators", "comment": null}, "epc_assessment_date": {"type": "date", "index": 32, "name": "epc_assessment_date", "comment": null}, "current_energy_efficiency_rating_band": {"type": "string", "index": 33, "name": "current_energy_efficiency_rating_band", "comment": null}, "heating_efficiency": {"type": "string", "index": 34, "name": "heating_efficiency", "comment": null}, "heating_type": {"type": "string", "index": 35, "name": "heating_type", "comment": null}, "co2_emissions_current_per_floor_area": {"type": "float", "index": 36, "name": "co2_emissions_current_per_floor_area", "comment": null}, "floor_energy_eff": {"type": "string", "index": 37, "name": "floor_energy_eff", "comment": null}, "mainheat_energy_eff": {"type": "string", "index": 38, "name": "mainheat_energy_eff", "comment": null}, "hot_water_energy_eff": {"type": "string", "index": 39, "name": "hot_water_energy_eff", "comment": null}, "lighting_energy_eff": {"type": "string", "index": 40, "name": "lighting_energy_eff", "comment": null}, "current_emissions": {"type": "float", "index": 41, "name": "current_emissions", "comment": null}, "photovoltaic_supply": {"type": "float", "index": 42, "name": "photovoltaic_supply", "comment": null}}, "stats": {"has_stats": {"id": "has_stats", "label": "Has Stats?", "value": false, "include": false, "description": "Indicates whether there are statistics for this table"}}, "unique_id": "source.Energy_model.grp_dataeng_dev.churn_address"}, "source.Energy_model.grp_dataeng_dev.churn_billing": {"metadata": {"type": "table", "schema": "grp_dataeng_dev", "name": "churn_billing", "database": "hive_metastore", "comment": null, "owner": "root"}, "columns": {"account_id": {"type": "integer", "index": 0, "name": "account_id", "comment": null}, "bill_id": {"type": "bigint", "index": 1, "name": "bill_id", "comment": null}, "charge_id": {"type": "bigint", "index": 2, "name": "charge_id", "comment": null}, "bill_line_item_id": {"type": "bigint", "index": 3, "name": "bill_line_item_id", "comment": null}, "statement_id": {"type": "bigint", "index": 4, "name": "statement_id", "comment": null}, "commodity_uid": {"type": "string", "index": 5, "name": "commodity_uid", "comment": null}, "account_transaction_id": {"type": "bigint", "index": 6, "name": "account_transaction_id", "comment": null}, "bill_amount": {"type": "float", "index": 7, "name": "bill_amount", "comment": null}, "bill_period_from": {"type": "date", "index": 8, "name": "bill_period_from", "comment": null}, "bill_period_to": {"type": "date", "index": 9, "name": "bill_period_to", "comment": null}, "bill_created_date": {"type": "date", "index": 10, "name": "bill_created_date", "comment": null}, "charge_start_date": {"type": "date", "index": 11, "name": "charge_start_date", "comment": null}, "charge_end_date": {"type": "date", "index": 12, "name": "charge_end_date", "comment": null}, "elec_bill_status": {"type": "string", "index": 13, "name": "elec_bill_status", "comment": null}, "elec_bill_type": {"type": "string", "index": 14, "name": "elec_bill_type", "comment": null}, "elec_standing_charge": {"type": "float", "index": 15, "name": "elec_standing_charge", "comment": null}, "elec_num_days_billing": {"type": "integer", "index": 16, "name": "elec_num_days_billing", "comment": null}, "elec_daily_unit_consumption": {"type": "float", "index": 17, "name": "elec_daily_unit_consumption", "comment": null}, "elec_Units_consumption": {"type": "float", "index": 18, "name": "elec_Units_consumption", "comment": null}, "gas_bill_status": {"type": "string", "index": 19, "name": "gas_bill_status", "comment": null}, "gas_bill_type": {"type": "string", "index": 20, "name": "gas_bill_type", "comment": null}, "gas_standing_charge": {"type": "float", "index": 21, "name": "gas_standing_charge", "comment": null}, "gas_num_days_billing": {"type": "integer", "index": 22, "name": "gas_num_days_billing", "comment": null}, "gas_Units_consumption": {"type": "float", "index": 23, "name": "gas_Units_consumption", "comment": null}, "gas_daily_unit_consumption": {"type": "float", "index": 24, "name": "gas_daily_unit_consumption", "comment": null}, "mpxn": {"type": "bigint", "index": 25, "name": "mpxn", "comment": null}, "unit_rate": {"type": "float", "index": 26, "name": "unit_rate", "comment": null}}, "stats": {"has_stats": {"id": "has_stats", "label": "Has Stats?", "value": false, "include": false, "description": "Indicates whether there are statistics for this table"}}, "unique_id": "source.Energy_model.grp_dataeng_dev.churn_billing"}, "source.Energy_model.grp_dataeng_dev.churn_complaint": {"metadata": {"type": "table", "schema": "grp_dataeng_dev", "name": "churn_complaint", "database": "hive_metastore", "comment": null, "owner": "root"}, "columns": {"customer_id": {"type": "string", "index": 0, "name": "customer_id", "comment": null}, "source_complaint_id": {"type": "string", "index": 1, "name": "source_complaint_id", "comment": null}, "complaint_type": {"type": "string", "index": 2, "name": "complaint_type", "comment": null}, "created_ts": {"type": "timestamp", "index": 3, "name": "created_ts", "comment": null}, "closed_ts": {"type": "timestamp", "index": 4, "name": "closed_ts", "comment": null}, "contact_reason_1": {"type": "string", "index": 5, "name": "contact_reason_1", "comment": null}, "contact_reason_2": {"type": "string", "index": 6, "name": "contact_reason_2", "comment": null}, "contact_reason_3": {"type": "string", "index": 7, "name": "contact_reason_3", "comment": null}, "source": {"type": "string", "index": 8, "name": "source", "comment": null}}, "stats": {"has_stats": {"id": "has_stats", "label": "Has Stats?", "value": false, "include": false, "description": "Indicates whether there are statistics for this table"}}, "unique_id": "source.Energy_model.grp_dataeng_dev.churn_complaint"}, "source.Energy_model.grp_dataeng_dev.churn_consumption": {"metadata": {"type": "table", "schema": "grp_dataeng_dev", "name": "churn_consumption", "database": "hive_metastore", "comment": null, "owner": "root"}, "columns": {"current_account_id": {"type": "integer", "index": 0, "name": "current_account_id", "comment": null}, "consumption_item_id": {"type": "integer", "index": 1, "name": "consumption_item_id", "comment": null}, "mpxn": {"type": "bigint", "index": 2, "name": "mpxn", "comment": null}, "meter_point_type": {"type": "string", "index": 3, "name": "meter_point_type", "comment": null}, "recorded_date": {"type": "date", "index": 4, "name": "recorded_date", "comment": null}, "recorded_ts": {"type": "timestamp", "index": 5, "name": "recorded_ts", "comment": null}, "charge_start_date": {"type": "date", "index": 6, "name": "charge_start_date", "comment": null}, "charge_end_date": {"type": "date", "index": 7, "name": "charge_end_date", "comment": null}, "actual_or_estimated": {"type": "string", "index": 8, "name": "actual_or_estimated", "comment": null}, "meter_reading_source": {"type": "string", "index": 9, "name": "meter_reading_source", "comment": null}, "start_end_date_units_consumed": {"type": "float", "index": 10, "name": "start_end_date_units_consumed", "comment": null}, "unit_type_uid": {"type": "string", "index": 11, "name": "unit_type_uid", "comment": null}, "start_end_date_units_rate": {"type": "float", "index": 12, "name": "start_end_date_units_rate", "comment": null}, "standing_charge": {"type": "float", "index": 13, "name": "standing_charge", "comment": null}, "start_end_date_billed_amount": {"type": "float", "index": 14, "name": "start_end_date_billed_amount", "comment": null}, "meter_reading_value": {"type": "float", "index": 15, "name": "meter_reading_value", "comment": null}, "daily_unit_consumption": {"type": "float", "index": 16, "name": "daily_unit_consumption", "comment": null}, "days_consumed": {"type": "integer", "index": 17, "name": "days_consumed", "comment": null}, "quantity_energy_consumed": {"type": "float", "index": 18, "name": "quantity_energy_consumed", "comment": null}}, "stats": {"has_stats": {"id": "has_stats", "label": "Has Stats?", "value": false, "include": false, "description": "Indicates whether there are statistics for this table"}}, "unique_id": "source.Energy_model.grp_dataeng_dev.churn_consumption"}, "source.Energy_model.grp_dataeng_dev.churn_customer": {"metadata": {"type": "table", "schema": "grp_dataeng_dev", "name": "churn_customer", "database": "hive_metastore", "comment": null, "owner": "root"}, "columns": {"customer_id": {"type": "string", "index": 0, "name": "customer_id", "comment": null}, "salutation": {"type": "string", "index": 1, "name": "salutation", "comment": null}, "vulrability": {"type": "integer", "index": 2, "name": "vulrability", "comment": null}, "marketing_consent": {"type": "string", "index": 3, "name": "marketing_consent", "comment": null}, "name": {"type": "string", "index": 4, "name": "name", "comment": null}, "email": {"type": "array", "index": 5, "name": "email", "comment": null}, "phone": {"type": "array", "index": 6, "name": "phone", "comment": null}, "gender": {"type": "string", "index": 7, "name": "gender", "comment": null}, "birth_dt": {"type": "timestamp", "index": 8, "name": "birth_dt", "comment": null}, "death_dt": {"type": "timestamp", "index": 9, "name": "death_dt", "comment": null}, "source_domain": {"type": "string", "index": 10, "name": "source_domain", "comment": null}}, "stats": {"has_stats": {"id": "has_stats", "label": "Has Stats?", "value": false, "include": false, "description": "Indicates whether there are statistics for this table"}}, "unique_id": "source.Energy_model.grp_dataeng_dev.churn_customer"}, "source.Energy_model.grp_dataeng_dev.churn_holding": {"metadata": {"type": "table", "schema": "grp_dataeng_dev", "name": "churn_holding", "database": "hive_metastore", "comment": null, "owner": "root"}, "columns": {"mpxn": {"type": "string", "index": 0, "name": "mpxn", "comment": null}, "customer_id": {"type": "string", "index": 1, "name": "customer_id", "comment": null}, "supply_start_dt": {"type": "date", "index": 2, "name": "supply_start_dt", "comment": null}, "supply_end_dt": {"type": "date", "index": 3, "name": "supply_end_dt", "comment": null}, "migration_dt": {"type": "date", "index": 4, "name": "migration_dt", "comment": null}, "address_id": {"type": "string", "index": 5, "name": "address_id", "comment": null}, "account_id": {"type": "string", "index": 6, "name": "account_id", "comment": null}, "product_category": {"type": "string", "index": 7, "name": "product_category", "comment": null}, "product_name": {"type": "string", "index": 8, "name": "product_name", "comment": null}, "product_start_dt": {"type": "date", "index": 9, "name": "product_start_dt", "comment": null}, "product_end_dt": {"type": "date", "index": 10, "name": "product_end_dt", "comment": null}, "source_domain": {"type": "string", "index": 11, "name": "source_domain", "comment": null}}, "stats": {"has_stats": {"id": "has_stats", "label": "Has Stats?", "value": false, "include": false, "description": "Indicates whether there are statistics for this table"}}, "unique_id": "source.Energy_model.grp_dataeng_dev.churn_holding"}, "source.Energy_model.grp_dataeng_dev.churn_interaction": {"metadata": {"type": "table", "schema": "grp_dataeng_dev", "name": "churn_interaction", "database": "hive_metastore", "comment": null, "owner": "root"}, "columns": {"interaction_id": {"type": "string", "index": 0, "name": "interaction_id", "comment": null}, "customer_id": {"type": "string", "index": 1, "name": "customer_id", "comment": null}, "direction": {"type": "string", "index": 2, "name": "direction", "comment": null}, "interaction_ts": {"type": "timestamp", "index": 3, "name": "interaction_ts", "comment": null}, "interaction_reason_l1": {"type": "string", "index": 4, "name": "interaction_reason_l1", "comment": null}, "interaction_reason_l2": {"type": "string", "index": 5, "name": "interaction_reason_l2", "comment": null}, "interaction_reason_l3": {"type": "string", "index": 6, "name": "interaction_reason_l3", "comment": null}, "connected_to_agent": {"type": "boolean", "index": 7, "name": "connected_to_agent", "comment": null}, "queue_time": {"type": "integer", "index": 8, "name": "queue_time", "comment": null}, "talk_time": {"type": "integer", "index": 9, "name": "talk_time", "comment": null}, "interaction_type": {"type": "string", "index": 10, "name": "interaction_type", "comment": null}, "interaction_source": {"type": "string", "index": 11, "name": "interaction_source", "comment": null}}, "stats": {"has_stats": {"id": "has_stats", "label": "Has Stats?", "value": false, "include": false, "description": "Indicates whether there are statistics for this table"}}, "unique_id": "source.Energy_model.grp_dataeng_dev.churn_interaction"}, "source.Energy_model.grp_dataeng_dev.churn_nps": {"metadata": {"type": "table", "schema": "grp_dataeng_dev", "name": "churn_nps", "database": "hive_metastore", "comment": null, "owner": "root"}, "columns": {"nps_survey_id": {"type": "string", "index": 0, "name": "nps_survey_id", "comment": null}, "customer_id": {"type": "string", "index": 1, "name": "customer_id", "comment": null}, "survey_ts": {"type": "timestamp", "index": 2, "name": "survey_ts", "comment": null}, "nps_score": {"type": "integer", "index": 3, "name": "nps_score", "comment": null}, "survey_type": {"type": "string", "index": 4, "name": "survey_type", "comment": null}, "source": {"type": "string", "index": 5, "name": "source", "comment": null}}, "stats": {"has_stats": {"id": "has_stats", "label": "Has Stats?", "value": false, "include": false, "description": "Indicates whether there are statistics for this table"}}, "unique_id": "source.Energy_model.grp_dataeng_dev.churn_nps"}}, "errors": null}